[
  {
    "ts": 1770787859.6971745,
    "run_date": "2026-02-05",
    "truck": 4,
    "seconds": 406
  },
  {
    "ts": 1770788708.0565255,
    "run_date": "2026-02-05",
    "truck": 4,
    "seconds": 62
  },
  {
    "ts": 1770789320.8804073,
    "run_date": "2026-02-05",
    "truck": 7,
    "seconds": 101
  },
  {
    "ts": 1770799790.6063066,
    "run_date": "2026-02-05",
    "truck": 73,
    "seconds": 174
  },
  {
    "ts": 1770800455.762044,
    "run_date": "2026-02-05",
    "truck": 57,
    "seconds": 74
  },
  {
    "ts": 1770800786.2139785,
    "run_date": "2026-02-05",
    "truck": 4,
    "seconds": 3
  },
  {
    "ts": 1770831239.0830908,
    "run_date": "2026-02-04",
    "truck": 7,
    "seconds": 3
  },
  {
    "ts": 1770831260.2068498,
    "run_date": "2026-02-04",
    "truck": 50,
    "seconds": 3
  },
  {
    "ts": 1770838022.8331597,
    "run_date": "2026-02-04",
    "truck": 60,
    "seconds": 5
  },
  {
    "ts": 1770838058.2402406,
    "run_date": "2026-02-04",
    "truck": 88,
    "seconds": 2
  },
  {
    "ts": 1770842309.9006572,
    "run_date": "2026-02-04",
    "truck": 4,
    "seconds": 4183
  },
  {
    "ts": 1770842314.1193264,
    "run_date": "2026-02-04",
    "truck": 69,
    "seconds": 1
  },
  {
    "ts": 1770842363.1280859,
    "run_date": "2026-02-04",
    "truck": 53,
    "seconds": 2
  },
  {
    "ts": 1770842371.16195,
    "run_date": "2026-02-04",
    "truck": 54,
    "seconds": 1
  },
  {
    "ts": 1770842378.8355122,
    "run_date": "2026-02-04",
    "truck": 89,
    "seconds": 1
  },
  {
    "ts": 1770842388.2137127,
    "run_date": "2026-02-04",
    "truck": 73,
    "seconds": 1
  },
  {
    "ts": 1770843098.8634722,
    "run_date": "2026-02-04",
    "truck": 56,
    "seconds": 623
  },
  {
    "ts": 1770844567.6225672,
    "run_date": "2026-02-04",
    "truck": 62,
    "seconds": 1463
  },
  {
    "ts": 1770844894.2444675,
    "run_date": "2026-02-04",
    "truck": 59,
    "seconds": 324
  },
  {
    "ts": 1770846379.380274,
    "run_date": "2026-02-04",
    "truck": 86,
    "seconds": 1482
  },
  {
    "ts": 1771176078.900513,
    "run_date": "2026-02-15",
    "truck": 101,
    "seconds": 111
  },
  {
    "ts": 1771176301.0189111,
    "run_date": "2026-02-15",
    "truck": 102,
    "seconds": 33
  },
  {
    "ts": 1771176479.366547,
    "run_date": "2026-02-15",
    "truck": 101,
    "seconds": 170
  },
  {
    "ts": 1771200967.617862,
    "run_date": "2026-02-15",
    "truck": 4,
    "seconds": 4844
  },
  {
    "ts": 1771202879.4245694,
    "run_date": "2026-02-15",
    "truck": 50,
    "seconds": 1587
  },
  {
    "ts": 1771202895.9224582,
    "run_date": "2026-02-15",
    "truck": 102,
    "seconds": 3
  },
  {
    "ts": 1771203995.5355573,
    "run_date": "2026-02-15",
    "truck": 101,
    "seconds": 5
  }
]